pyray/__init__.py
pyray/__init__.pyi
pyray/py.typed
raylib/SDL3.dll
raylib/__init__.py
raylib/__init__.pyi
raylib/_raylib_cffi.cp310-win32.pyd
raylib/build.py
raylib/colors.py
raylib/defines.py
raylib/enums.py
raylib/glfw3.h.modified
raylib/physac.h.modified
raylib/py.typed
raylib/raygui.h.modified
raylib/raylib.h.modified
raylib/raymath.h.modified
raylib/rlgl.h.modified
raylib/version.py
raylib_software-5.6.0.0.dev3.dist-info/licenses/LICENSE
raylib_software-5.6.0.0.dev3.dist-info/METADATA
raylib_software-5.6.0.0.dev3.dist-info/WHEEL
raylib_software-5.6.0.0.dev3.dist-info/top_level.txt
raylib_software-5.6.0.0.dev3.dist-info/RECORD
