Metadata-Version: 2.1
Name: raylib_software
Version: 5.6.0.0.dev3
Summary: Python CFFI bindings for Raylib
Home-page: https://github.com/electronstudio/raylib-python-cffi
Author: Electron Studio
Author-email: github@electronstudio.co.uk
Classifier: Programming Language :: Python :: 3
Classifier: Programming Language :: Python :: 3.14
Classifier: Programming Language :: Python :: 3.13
Classifier: Programming Language :: Python :: 3.12
Classifier: Programming Language :: Python :: 3.11
Classifier: Programming Language :: Python :: 3.10
Classifier: Programming Language :: Python :: 3.9
Classifier: Programming Language :: Python :: 3.8
Classifier: Programming Language :: Python :: 3.7
License-File: LICENSE
Requires-Dist: cffi >=1.15.1
